Workbook

Sheet 生存汉语词汇表
A1: 序号 | B1: 课次 | C1: 课文 | D1: 汉字 | E1: 拼音 | F1: 英文解释 | G1: 例句1（中文） | H1: 例句1（英文） | I1: 例句2（中文） | J1: 例句2（英文） | K1: 备注 | L1: 最常见词语搭配
A2: 1 | B2: 4 | C2: 看菜单 | D2: 你好 | E2: nǐ hǎo | F2: hello; how are you | G2: 你好！ | H2: Hello! | I2: 老师，你好！ | J2: Hello, teacher! | L2: 你好老师；你好朋友；你好，请问
A3: 2 | B3: 4 | C3: 看菜单 | D3: 吃 | E3: chī | F3: eat | G3: 我想吃饭。 | H3: I want to eat. | I3: 我们可以吃饭吗？ | J3: Can we eat now? | L3: 吃饭；吃菜；吃早饭
A4: 3 | B4: 4 | C4: 看菜单 | D4: 什么 | E4: shénme | F4: what | G4: 这是什么？ | H4: What is this? | I4: 你吃什么？ | J4: What do you eat? | L4: 什么东西；什么时候；为什么
A5: 4 | B5: 4 | C5: 看菜单 | D5: 有（没有） | E5: yǒu (méiyǒu) | F5: have; exist (negative: not have) | G5: 这里有水。 | H5: There is water here. | I5: 这里没有咖啡。 | J5: There is no coffee here. | L5: 有时间；有朋友；没有问题
A6: 5 | B6: 4 | C6: 看菜单 | D6: 菜单 | E6: càidān | F6: menu | G6: 这是菜单。 | H6: This is the menu. | I6: 请给我看一下菜单。 | J6: Please show me the menu. | L6: 看菜单；菜单上；一份菜单
A7: 6 | B7: 4 | C7: 看菜单 | D7: 吗 | E7: ma | F7: question particle for yes/no questions | G7: 你好吗？ | H7: Are you well? | I7: 这里有水吗？ | J7: Is there water here? | L7: 好吗；有吗；可以吗
A8: 7 | B8: 4 | C8: 看菜单 | D8: 给 | E8: gěi | F8: give | G8: 请给我水。 | H8: Please give me water. | I8: 我给你一个。 | J8: I will give you one. | L8: 给我；给你；送给
A9: 8 | B9: 4 | C9: 看菜单 | D9: 这个 | E9: zhège | F9: this | G9: 这个很好。 | H9: This is very good. | I9: 我要这个。 | J9: I want this one. | L9: 这个人；这个地方；这个时候
A10: 9 | B10: 4 | C10: 看菜单 | D10: 叫 | E10: jiào | F10: call; be called | G10: 我叫小王。 | H10: My name is Xiao Wang. | I10: 我叫一辆车。 | J10: I will call a car. | L10: 叫名字；叫车；叫外卖
A11: 10 | B11: 4 | C11: 看菜单 | D11: 那个 | E11: nàge | F11: that | G11: 那个多少钱？ | H11: How much is that one? | I11: 我不要那个。 | J11: I do not want that one. | L11: 那个人；那个地方；那个时候
A12: 11 | B12: 4 | C12: 看菜单 | D12: 是 | E12: shì | F12: be; is/am/are | G12: 我是学生。 | H12: I am a student. | I12: 这是我的。 | J12: This is mine. | L12: 我是；这是；不是
A13: 12 | B13: 4 | C13: 看菜单 | D13: 要 | E13: yào | F13: want; would like | G13: 我要水。 | H13: I want water. | I13: 我要去学校。 | J13: I want to go to school. | L13: 想要；需要；要去
... A16: 15 | B16: 4 | C16: 看菜单 | D16: 这里 | E16: zhèlǐ | F16: here | G16: 我住这里。 | H16: I live here. | I16: 这里有地铁站。 | J16: There is a subway station here. | L16: 在这里；这里有；这里是
A17: 16 | B17: 4 | C17: 看菜单 | D17: 宫保鸡丁 | E17: gōngbǎo jīdīng | F17: kung pao chicken | G17: 我想吃宫保鸡丁。 | H17: I want to eat kung pao chicken. | I17: 我要一份宫保鸡丁。 | J17: I'd like one serving of kung pao chicken. | K17: 教材标*菜名 | L17: 吃宫保鸡丁；一份宫保鸡丁；喜欢宫保鸡丁
A18: 17 | B18: 4 | C18: 看菜单 | D18: 拉面 | E18: lāmiàn | F18: lamian; hand-pulled noodles | G18: 我想吃拉面。 | H18: I want to eat lamian. | I18: 我要一份拉面。 | J18: I'd like one serving of lamian. | K18: 教材标*菜名 | L18: 吃拉面；一份拉面；喜欢拉面
A19: 18 | B19: 4 | C19: 看菜单 | D19: 在 | E19: zài | F19: at; in; on | G19: 我在家。 | H19: I am at home. | I19: 他在学校。 | J19: He is at school. | L19: 在家；在学校；在这里
A20: 19 | B20: 4 | C20: 看菜单 | D20: 这儿 | E20: zhèr | F20: here | G20: 我在这儿。 | H20: I am here. | I20: 这儿有水。 | J20: There is water here. | L20: 在这儿；这儿有；来这儿
A21: 20 | B21: 4 | C21: 看菜单 | D21: 还是 | E21: háishì | F21: or (in a question) | G21: 你喝茶还是咖啡？ | H21: Do you drink tea or coffee? | I21: 坐地铁还是坐公交车？ | J21: Take the subway or the bus? | L21: 还是不；还是要；还是喜欢
A22: 21 | B22: 4 | C22: 看菜单 | D22: 打包 | E22: dǎbāo | F22: pack to go; take away | G22: 我想打包这个菜。 | H22: I want to take this dish to go. | I22: 我们可以打包这个菜吗？ | J22: Can we take this to go? | L22: 打包带走；帮我打包；可以打包
A23: 22 | B23: 4 | C23: 看菜单 | D23: 服务员 | E23: fúwùyuán | F23: waiter; waitress; server | G23: 他是服务员。 | H23: He is a waiter. | I23: 我认识一位服务员。 | J23: I know a waiter. | L23: 一位服务员；找服务员；服务员来了
A24: 23 | B24: 4 | C24: 看菜单 | D24: 买单 | E24: mǎidān | F24: pay the bill | G24: 我想买单。 | H24: I would like to pay the bill. | I24: 我们可以买单吗？ | J24: Can we pay the bill? | L24: 服务员买单；请买单；买单结账
A25: 24 | B25: 4 | C25: 看菜单 | D25: 一共 | E25: yígòng | F25: in total | G25: 一共五十块。 | H25: It is 50 yuan in total. | I25: 我们一共三个人。 | J25: There are three of us in total. | L25: 一共多少钱；一共有；一共需要
A26: 25 | B26: 4 | C26: 看菜单 | D26: 多少钱 | E26: duōshao qián | F26: how much | G26: 这个多少钱？ | H26: How much is this? | I26: 一斤苹果多少钱？ | J26: How much is a jin of apples? | L26: 多少钱一个；多少钱一斤；一共多少钱
A27: 26 | B27: 4 | C27: 看菜单 | D27: 块/元 | E27: kuài/yuán | F27: yuan (RMB); colloquial/formal money unit | G27: 这个十块。 | H27: This is ten yuan. | I27: 一共五十元。 | J27: The total is 50 yuan. | L27: 十块钱；二十元；一百元
A28: 27 | B28: 5 | C28: 描述菜品味道 | D28: 辣 | E28: là | F28: spicy | G28: 这个很辣。 | H28: This is very spicy. | I28: 那个不太辣。 | J28: That one is not very spicy. | L28: 很辣；比较辣；太辣了
A29: 28 | B29: 5 | C29: 描述菜品味道 | D29: 很 | E29: hěn | F29: very | G29: 这个很好。 | H29: This is very good. | I29: 今天很热。 | J29: It is very hot today. | L29: 很好；很喜欢；很漂亮
A30: 29 | B30: 5 | C30: 描述菜品味道 | D30: 不 | E30: bù | F30: not; no | G30: 我不去。 | H30: I am not going. | I30: 这个不贵。 | J30: This is not expensive. | L30: 不是；不要；不喜欢
... A32: 31 | B32: 5 | C32: 描述菜品味道 | D32: 甜 | E32: tián | F32: sweet | G32: 这个很甜。 | H32: This is very sweet. | I32: 那个不太甜。 | J32: That one is not very sweet. | L32: 很甜；比较甜；太甜了
A33: 32 | B33: 5 | C33: 描述菜品味道 | D33: 回锅肉 | E33: huíguōròu | F33: twice-cooked pork | G33: 我想吃回锅肉。 | H33: I want to eat twice-cooked pork. | I33: 我要一份回锅肉。 | J33: I'd like one serving of twice-cooked pork. | K33: 教材菜名 | L33: 吃回锅肉；一份回锅肉；喜欢回锅肉
A34: 33 | B34: 5 | C34: 描述菜品味道 | D34: 喜欢 | E34: xǐhuān | F34: like | G34: 我想喜欢这个菜。 | H34: I like this dish. | I34: 我们可以喜欢这个菜吗？ | J34: Do you like this dish? | L34: 很喜欢；最喜欢；喜欢吃
A35: 34 | B35: 5 | C35: 描述菜品味道 | D35: 也 | E35: yě | F35: also | G35: 我也喜欢。 | H35: I like it too. | I35: 他也是学生。 | J35: He is also a student. | L35: 也好；也可以；也喜欢
A36: 35 | B36: 5 | C36: 描述菜品味道 | D36: 但是 | E36: dànshì | F36: but | G36: 我喜欢，但是有点儿贵。 | H36: I like it, but it is a little expensive. | I36: 他想去，但是没时间。 | J36: He wants to go, but he has no time. | L36: 但是我；但是不；虽然…但是…
A37: 36 | B37: 5 | C37: 描述菜品味道 | D37: 更 | E37: gèng | F37: more; even more | G37: 这个更好。 | H37: This one is better. | I37: 今天更冷。 | J37: It is colder today. | L37: 更好；更多；更方便
A38: 37 | B38: 5 | C38: 描述菜品味道 | D38: 过 | E38: guò | F38: aspect particle: have done before | G38: 我去过北京。 | H38: I have been to Beijing. | I38: 请过马路。 | J38: Please cross the road. | L38: 去过；吃过；过马路
A39: 38 | B39: 5 | C39: 描述菜品味道 | D39: 的 | E39: de | F39: structural particle | G39: 这是我的。 | H39: This is mine. | I39: 红色的很好看。 | J39: The red one looks nice. | L39: 我的；红色的；新的
A40: 39 | B40: 5 | C40: 描述菜品味道 | D40: 酸甜 | E40: suāntián | F40: sweet and sour | G40: 这个很酸甜。 | H40: This is very sweet and sour. | I40: 那个不太酸甜。 | J40: That one is not very sweet and sour. | L40: 很酸甜；比较酸甜；太酸甜了
A41: 40 | B41: 5 | C41: 描述菜品味道 | D41: 呢 | E41: ne | F41: particle used in questions/topics | G41: 你呢？ | H41: And you? | I41: 他在哪儿呢？ | J41: Where is he? | L41: 你呢；在哪儿呢；怎么样呢
A42: 41 | B42: 5 | C42: 描述菜品味道 | D42: 特别 | E42: tèbié | F42: especially; special | G42: 这个特别好。 | H42: This is especially good. | I42: 我特别喜欢。 | J42: I especially like it. | L42: 特别好；特别喜欢；特别方便
A43: 42 | B43: 5 | C43: 描述菜品味道 | D43: 下次 | E43: xiàcì | F43: next time | G43: 下次见！ | H43: See you next time! | I43: 我们下次再去。 | J43: We will go again next time. | L43: 下次见；下次再说；下次来
A44: 43 | B44: 5 | C44: 描述菜品味道 | D44: 请 | E44: qǐng | F44: please; invite; treat | G44: 请坐。 | H44: Please sit down. | I44: 请进。 | J44: Please come in. | L44: 请问；请坐；请进
A45: 44 | B45: 5 | C45: 描述菜品味道 | D45: 吧 | E45: ba | F45: sentence-final particle for suggestion/softening | G45: 我们走吧。 | H45: Let us go. | I45: 坐这儿吧。 | J45: Sit here. | L45: 走吧；好吧；来吧
... A47: 46 | B47: 5 | C47: 描述菜品味道 | D47: 啊 | E47: a | F47: sentence-final particle showing feeling | G47: 好啊！ | H47: Great! | I47: 是啊。 | J47: Yes. | L47: 好啊；是啊；对啊
A48: 47 | B48: 5 | C48: 描述菜品味道 | D48: 锅包肉 | E48: guōbāoròu | F48: sweet and sour pork | G48: 我想吃锅包肉。 | H48: I want to eat sweet and sour pork. | I48: 我要一份锅包肉。 | J48: I'd like one serving of sweet and sour pork. | K48: 教材标*菜名 | L48: 吃锅包肉；一份锅包肉；喜欢锅包肉
A49: 48 | B49: 5 | C49: 描述菜品味道 | D49: 水煮肉片 | E49: shuǐzhǔ ròupiàn | F49: Sichuan spicy boiled pork slices | G49: 我想吃水煮肉片。 | H49: I want to eat Sichuan spicy boiled pork slices. | I49: 我要一份水煮肉片。 | J49: I'd like one serving of Sichuan spicy boiled pork slices. | K49: 教材标*菜名 | L49: 吃水煮肉片；一份水煮肉片；喜欢水煮肉片
A50: 49 | B50: 6 | C50: 餐具 | D50: 掉 | E50: diào | F50: fall; drop | G50: 筷子掉了。 | H50: The chopsticks fell. | I50: 我的手机掉在地上了。 | J50: My phone fell on the floor. | L50: 掉在地上；掉了；别掉了
A51: 50 | B51: 6 | C51: 餐具 | D51: 地上 | E51: dìshang | F51: on the ground | G51: 筷子掉在地上了。 | H51: The chopsticks fell on the floor. | I51: 包在地上。 | J51: The bag is on the floor. | L51: 在地上；掉在地上；放在地上
A52: 51 | B52: 6 | C52: 餐具 | D52: 给 | E52: gěi | F52: give | G52: 请给我水。 | H52: Please give me water. | I52: 我给你一个。 | J52: I will give you one. | L52: 给我；给你；送给
A53: 52 | B53: 6 | C53: 餐具 | D53: 稍等 | E53: shāoděng | F53: wait a moment | G53: 请稍等。 | H53: Please wait a moment. | I53: 稍等一下。 | J53: Wait a moment, please. | L53: 请稍等；稍等一下；您稍等
A54: 53 | B54: 6 | C54: 餐具 | D54: 一双筷子 | E54: yì shuāng kuàizi | F54: a pair of chopsticks | G54: 请给我一双筷子。 | H54: Please give me a pair of chopsticks. | I54: 桌上有一双筷子。 | J54: There is a pair of chopsticks on the table. | L54: 一双筷子；拿筷子；给我筷子
A55: 54 | B55: 6 | C55: 餐具 | D55: 一个碗 | E55: yí ge wǎn | F55: a bowl | G55: 请给我一个碗。 | H55: Please give me a bowl. | I55: 这里有一个碗。 | J55: There is a bowl here. | L55: 一个碗；一碗饭；拿一个碗
A56: 55 | B56: 6 | C56: 餐具 | D56: 再 | E56: zài | F56: again | G56: 请再说一次。 | H56: Please say it again. | I56: 我们下次再来。 | J56: We will come again next time. | L56: 再见；再说；再来
A57: 56 | B57: 6 | C57: 餐具 | D57: 北京烤鸭 | E57: Běijīng kǎoyā | F57: Peking roast duck | G57: 我想吃北京烤鸭。 | H57: I want to eat Peking roast duck. | I57: 我要一份北京烤鸭。 | J57: I'd like one serving of Peking roast duck. | K57: 教材标*菜名 | L57: 吃北京烤鸭；一份北京烤鸭；喜欢北京烤鸭
A58: 57 | B58: 7 | C58: 菜名和食材 | D58: 主意 | E58: zhǔyì | F58: idea | G58: 这个主意很好。 | H58: This is a good idea. | I58: 我有一个主意。 | J58: I have an idea. | L58: 好主意；一个主意；有主意
A59: 58 | B59: 7 | C59: 菜名和食材 | D59: 好久 | E59: hǎojiǔ | F59: a long time | G59: 好久不见！ | H59: Long time no see! | I59: 我等了好久。 | J59: I waited for a long time. | L59: 好久不见；等了好久；好久以前
A60: 59 | B60: 7 | C60: 菜名和食材 | D60: 猪肉 | E60: zhūròu | F60: pork | G60: 我想吃猪肉。 | H60: I want to eat pork. | I60: 我要一份猪肉。 | J60: I'd like one serving of pork. | L60: 吃猪肉；一份猪肉；喜欢猪肉
A61: 60 | B61: 7 | C61: 菜名和食材 | D61: 猪肝 | E61: zhūgān | F61: pork liver | G61: 我想吃猪肝。 | H61: I want to eat pork liver. | I61: 我要一份猪肝。 | J61: I'd like one serving of pork liver. | L61: 吃猪肝；一份猪肝；喜欢猪肝
A62: 61 | B62: 7 | C62: 菜名和食材 | D62: 牛 | E62: niú | F62: ox; cow; beef (radical/ingredient clue) | G62: 我想吃牛肉。 | H62: I want to eat beef. | I62: 这是牛肉。 | J62: This is beef. | L62: 牛肉；牛肉面；铁板牛肉
A63: 62 | B63: 7 | C63: 菜名和食材 | D63: 羊 | E63: yáng | F63: sheep; mutton (radical/ingredient clue) | G63: 我想吃羊肉。 | H63: I want to eat mutton. | I63: 这是羊肉。 | J63: This is mutton. | L63: 羊肉；羊肉汤；白切羊肉
A64: 63 | B64: 7 | C64: 菜名和食材 | D64: 宫保鸡丁 | E64: gōngbǎo jīdīng | F64: kung pao chicken | G64: 我想吃宫保鸡丁。 | H64: I want to eat kung pao chicken. | I64: 我要一份宫保鸡丁。 | J64: I'd like one serving of kung pao chicken. | K64: 教材标*菜名 | L64: 吃宫保鸡丁；一份宫保鸡丁；喜欢宫保鸡丁
A65: 64 | B65: 7 | C65: 菜名和食材 | D65: 水煮鱼 | E65: shuǐzhǔyú | F65: Sichuan spicy boiled fish | G65: 我想吃水煮鱼。 | H65: I want to eat Sichuan spicy boiled fish. | I65: 我要一份水煮鱼。 | J65: I'd like one serving of Sichuan spicy boiled fish. | K65: 教材标*菜名 | L65: 吃水煮鱼；一份水煮鱼；喜欢水煮鱼
A66: 65 | B66: 7 | C66: 菜名和食材 | D66: 回锅肉 | E66: huíguōròu | F66: twice-cooked pork | G66: 我想吃回锅肉。 | H66: I want to eat twice-cooked pork. | I66: 我要一份回锅肉。 | J66: I'd like one serving of twice-cooked pork. | K66: 教材菜名 | L66: 吃回锅肉；一份回锅肉；喜欢回锅肉
A67: 66 | B67: 7 | C67: 菜名和食材 | D67: 爆炒猪肝 | E67: bàochǎo zhūgān | F67: stir-fried pork liver | G67: 我想吃爆炒猪肝。 | H67: I want to eat stir-fried pork liver. | I67: 我要一份爆炒猪肝。 | J67: I'd like one serving of stir-fried pork liver. | K67: 教材标*菜名 | L67: 吃爆炒猪肝；一份爆炒猪肝；喜欢爆炒猪肝
A68: 67 | B68: 7 | C68: 菜名和食材 | D68: 铁板牛肉 | E68: tiěbǎn niúròu | F68: sizzling beef | G68: 我想吃铁板牛肉。 | H68: I want to eat sizzling beef. | I68: 我要一份铁板牛肉。 | J68: I'd like one serving of sizzling beef. | K68: 教材标*菜名 | L68: 吃铁板牛肉；一份铁板牛肉；喜欢铁板牛肉
A69: 68 | B69: 7 | C69: 菜名和食材 | D69: 白切羊肉 | E69: báiqiē yángròu | F69: sliced boiled mutton | G69: 我想吃白切羊肉。 | H69: I want to eat sliced boiled mutton. | I69: 我要一份白切羊肉。 | J69: I'd like one serving of sliced boiled mutton. | K69: 教材标*菜名 | L69: 吃白切羊肉；一份白切羊肉；喜欢白切羊肉
A70: 69 | B70: 7 | C70: 菜名和食材 | D70: 蔬菜 | E70: shūcài | F70: vegetable | G70: 我想吃蔬菜。 | H70: I want to eat vegetable. | I70: 我要一份蔬菜。 | J70: I'd like one serving of vegetable. | L70: 吃蔬菜；一份蔬菜；喜欢蔬菜
A71: 70 | B71: 7 | C71: 菜名和食材 | D71: 素食者 | E71: sùshízhě | F71: vegetarian | G71: 他是素食者。 | H71: He is a vegetarian. | I71: 我认识一位素食者。 | J71: I know a vegetarian. | L71: 一位素食者；找素食者；素食者来了
A72: 71 | B72: 7 | C72: 菜名和食材 | D72: 豆芽 | E72: dòuyá | F72: bean sprouts | G72: 我想吃豆芽。 | H72: I want to eat bean sprouts. | I72: 我要一份豆芽。 | J72: I'd like one serving of bean sprouts. | L72: 吃豆芽；一份豆芽；喜欢豆芽
A73: 72 | B73: 7 | C73: 菜名和食材 | D73: 牡蛎 | E73: mǔlì | F73: oyster | G73: 我想吃牡蛎。 | H73: I want to eat oyster. | I73: 我要一份牡蛎。 | J73: I'd like one serving of oyster. | L73: 吃牡蛎；一份牡蛎；喜欢牡蛎
A74: 73 | B74: 7 | C74: 菜名和食材 | D74: 豆腐 | E74: dòufu | F74: tofu | G74: 我想吃豆腐。 | H74: I want to eat tofu. | I74: 我要一份豆腐。 | J74: I'd like one serving of tofu. | L74: 吃豆腐；一份豆腐；喜欢豆腐
A75: 74 | B75: 7 | C75: 菜名和食材 | D75: 汤 | E75: tāng | F75: soup | G75: 我想喝汤。 | H75: I would like some soup. | I75: 这个汤很好喝。 | J75: This soup tastes good. | L75: 喝汤；一碗汤；鸡蛋汤
A76: 75 | B76: 7 | C76: 菜名和食材 | D76: 海鲜 | E76: hǎixiān | F76: seafood | G76: 我想吃海鲜。 | H76: I want to eat seafood. | I76: 我要一份海鲜。 | J76: I'd like one serving of seafood. | L76: 吃海鲜；一份海鲜；喜欢海鲜
A77: 76 | B77: 7 | C77: 菜名和食材 | D77: 过敏 | E77: guòmǐn | F77: be allergic to; allergy | G77: 我对海鲜过敏。 | H77: I am allergic to seafood. | I77: 你对什么过敏？ | J77: What are you allergic to? | L77: 对海鲜过敏；食物过敏；过敏了
A78: 77 | B78: 7 | C78: 菜名和食材 | D78: 换 | E78: huàn | F78: change; replace | G78: 我想换一个。 | H78: I want to change it. | I78: 我们可以换一个吗？ | J78: Can we change it? | L78: 换一个；换房间；换钱
A79: 78 | B79: 7 | C79: 菜名和食材 | D79: 西红柿 | E79: xīhóngshì | F79: tomato | G79: 我想吃西红柿。 | H79: I want to eat tomato. | I79: 我要一份西红柿。 | J79: I'd like one serving of tomato. | L79: 吃西红柿；一份西红柿；喜欢西红柿
A80: 79 | B80: 7 | C80: 菜名和食材 | D80: 鸡蛋 | E80: jīdàn | F80: egg | G80: 我想吃鸡蛋。 | H80: I want to eat egg. | I80: 我要一份鸡蛋。 | J80: I'd like one serving of egg. | L80: 吃鸡蛋；一份鸡蛋；喜欢鸡蛋
A81: 80 | B81: 7 | C81: 菜名和食材 | D81: 芋头 | E81: yùtou | F81: taro | G81: 我想吃芋头。 | H81: I want to eat taro. | I81: 我要一份芋头。 | J81: I'd like one serving of taro. | L81: 吃芋头；一份芋头；喜欢芋头
A82: 81 | B82: 7 | C82: 菜名和食材 | D82: 脆 | E82: cuì | F82: crispy | G82: 这个很脆。 | H82: This is very crispy. | I82: 那个不太脆。 | J82: That one is not very crispy. | L82: 很脆；比较脆；太脆了
A83: 82 | B83: 7 | C83: 菜名和食材 | D83: 干锅花菜 | E83: gānguō huācài | F83: dry-pot cauliflower | G83: 我想吃干锅花菜。 | H83: I want to eat dry-pot cauliflower. | I83: 我要一份干锅花菜。 | J83: I'd like one serving of dry-pot cauliflower. | K83: 教材标*菜名 | L83: 吃干锅花菜；一份干锅花菜；喜欢干锅花菜
A84: 83 | B84: 7 | C84: 菜名和食材 | D84: 清炒豆芽 | E84: qīngchǎo dòuyá | F84: stir-fried bean sprouts | G84: 我想吃清炒豆芽。 | H84: I want to eat stir-fried bean sprouts. | I84: 我要一份清炒豆芽。 | J84: I'd like one serving of stir-fried bean sprouts. | K84: 教材标*菜名 | L84: 吃清炒豆芽；一份清炒豆芽；喜欢清炒豆芽
A85: 84 | B85: 7 | C85: 菜名和食材 | D85: 牡蛎豆腐汤 | E85: mǔlì dòufu tāng | F85: oyster and tofu soup | G85: 我想吃牡蛎豆腐汤。 | H85: I want to eat oyster and tofu soup. | I85: 我要一份牡蛎豆腐汤。 | J85: I'd like one serving of oyster and tofu soup. | K85: 教材标*菜名 | L85: 吃牡蛎豆腐汤；一份牡蛎豆腐汤；喜欢牡蛎豆腐汤
A86: 85 | B86: 7 | C86: 菜名和食材 | D86: 西红柿鸡蛋汤 | E86: xīhóngshì jīdàn tāng | F86: tomato and egg soup | G86: 我想吃西红柿鸡蛋汤。 | H86: I want to eat tomato and egg soup. | I86: 我要一份西红柿鸡蛋汤。 | J86: I'd like one serving of tomato and egg soup. | K86: 教材标*菜名 | L86: 吃西红柿鸡蛋汤；一份西红柿鸡蛋汤；喜欢西红柿鸡蛋汤
A87: 86 | B87: 7 | C87: 菜名和食材 | D87: 拔丝芋头 | E87: básī yùtou | F87: caramelized taro | G87: 我想吃拔丝芋头。 | H87: I want to eat caramelized taro. | I87: 我要一份拔丝芋头。 | J87: I'd like one serving of caramelized taro. | K87: 教材标*菜名 | L87: 吃拔丝芋头；一份拔丝芋头；喜欢拔丝芋头
A88: 87 | B88: 8 | C88: 在餐馆用餐 | D88: 位 | E88: wèi | F88: measure word for people (polite) | G88: 一位老师来了。 | H88: A teacher has arrived. | I88: 这位是王老师。 | J88: This is Teacher Wang. | L88: 一位老师；这位先生；两位客人
A89: 88 | B89: 8 | C89: 在餐馆用餐 | D89: 这边请 | E89: zhèbiān qǐng | F89: this way, please | G89: 这边请。 | H89: This way, please. | I89: 您好，这边请。 | J89: Hello. This way, please. | L89: 这边请；请这边走；您这边请
A90: 89 | B90: 8 | C90: 在餐馆用餐 | D90: 请坐 | E90: qǐng zuò | F90: please sit down | G90: 请坐。 | H90: Please sit down. | I90: 您请坐。 | J90: Please have a seat. | L90: 请坐；请坐这边；您请坐
A91: 90 | B91: 8 | C91: 在餐馆用餐 | D91: 三鲜 | E91: sānxiān | F91: three-delicacy filling/dish | G91: 我想吃三鲜。 | H91: I want to eat three-delicacy filling/dish. | I91: 我要一份三鲜。 | J91: I'd like one serving of three-delicacy filling/dish. | L91: 吃三鲜；一份三鲜；喜欢三鲜
A92: 91 | B92: 8 | C92: 在餐馆用餐 | D92: 饺子 | E92: jiǎozǐ | F92: dumpling | G92: 我想吃饺子。 | H92: I want to eat dumpling. | I92: 我要一份饺子。 | J92: I'd like one serving of dumpling. | L92: 吃饺子；一份饺子；喜欢饺子
A93: 92 | B93: 8 | C93: 在餐馆用餐 | D93: 虾仁 | E93: xiārén | F93: shrimp meat; shelled shrimp | G93: 我想吃虾仁。 | H93: I want to eat shrimp meat. | I93: 我要一份虾仁。 | J93: I'd like one serving of shrimp meat. | L93: 吃虾仁；一份虾仁；喜欢虾仁
A94: 93 | B94: 8 | C94: 在餐馆用餐 | D94: 虾 | E94: xiā | F94: shrimp | G94: 我想吃虾。 | H94: I want to eat shrimp. | I94: 我要一份虾。 | J94: I'd like one serving of shrimp. | L94: 吃虾；一份虾；喜欢虾
A95: 94 | B95: 8 | C95: 在餐馆用餐 | D95: 试一下 | E95: shì yíxià | F95: have a try; try it | G95: 我想试一下这个。 | H95: I want to try this. | I95: 我们可以试一下这个吗？ | J95: Can we try this? | L95: 试一下；让我试一下；可以试一下
A96: 95 | B96: 8 | C96: 在餐馆用餐 | D96: 啤酒 | E96: píjiǔ | F96: beer | G96: 我想喝啤酒。 | H96: I would like a beer. | I96: 还要一瓶啤酒。 | J96: I would like another bottle of beer. | L96: 喝啤酒；一瓶啤酒；冰啤酒
A97: 96 | B97: 8 | C97: 在餐馆用餐 | D97: 还要 | E97: háiyào | F97: want more; also want | G97: 我还要一杯水。 | H97: I also want a glass of water. | I97: 还要别的吗？ | J97: Would you like anything else? | L97: 还要一个；还要什么；还要不要
A98: 97 | B98: 8 | C98: 在餐馆用餐 | D98: 别的 | E98: biéde | F98: other; else | G98: 还有别的吗？ | H98: Is there anything else? | I98: 我想看别的。 | J98: I want to see another one. | L98: 别的人；别的地方；别的颜色
A99: 98 | B99: 8 | C99: 在餐馆用餐 | D99: 请慢用 | E99: qǐng màn yòng | F99: please enjoy your meal | G99: 请慢用。 | H99: Please enjoy your meal. | I99: 菜来了，请慢用。 | J99: Here is your food. Enjoy your meal. | L99: 请慢用；慢慢吃；您慢用
... A115: 114 | B115: 9 | C115: 方位和地址 | D115: 大厦 | E115: dàshà | F115: building; mansion | G115: 我去大厦。 | H115: I am going to building. | I115: 大厦在哪儿？ | J115: Where is building? | L115: 去大厦；在大厦；大厦附近
A116: 115 | B116: 9 | C116: 方位和地址 | D116: 南华市 | E116: Nánhuá Shì | F116: Nanhua City (fictional) | G116: 我去南华市。 | H116: I am going to Nanhua City. | I116: 南华市在哪儿？ | J116: Where is Nanhua City? | K116: 教材标*专名 | L116: 去南华市；在南华市；南华市附近
A117: 116 | B117: 9 | C117: 方位和地址 | D117: 凤凰花园 | E117: Fènghuáng Huāyuán | F117: Fenghuang Garden | G117: 我去凤凰花园。 | H117: I am going to Fenghuang Garden. | I117: 凤凰花园在哪儿？ | J117: Where is Fenghuang Garden? | K117: 教材标*专名 | L117: 去凤凰花园；在凤凰花园；凤凰花园附近
A118: 117 | B118: 9 | C118: 方位和地址 | D118: 泰山路 | E118: Tàishān Lù | F118: Taishan Road | G118: 我去泰山路。 | H118: I am going to Taishan Road. | I118: 泰山路在哪儿？ | J118: Where is Taishan Road? | K118: 教材标*专名 | L118: 去泰山路；在泰山路；泰山路附近
A119: 118 | B119: 9 | C119: 方位和地址 | D119: 华山大厦 | E119: Huàshān Dàshà | F119: Huashan Mansion | G119: 我去华山大厦。 | H119: I am going to Huashan Mansion. | I119: 华山大厦在哪儿？ | J119: Where is Huashan Mansion? | K119: 教材标*专名 | L119: 去华山大厦；在华山大厦；华山大厦附近
...

Sheet 课次统计
A1: 课次 | B1: 课文 | C1: 词条数 | D1: 教材PDF词汇页
A2: 4 | B2: 看菜单 | C2: =COUNTIF(生存汉语词汇表!$B$2:$B$641,A2) -> 26 | D2: 13、15
A3: 5 | B3: 描述菜品味道 | C3: =COUNTIF(生存汉语词汇表!$B$2:$B$641,A3) -> 22 | D3: 18、19、20
A4: 6 | B4: 餐具 | C4: =COUNTIF(生存汉语词汇表!$B$2:$B$641,A4) -> 8 | D4: 24
A5: 7 | B5: 菜名和食材 | C5: =COUNTIF(生存汉语词汇表!$B$2:$B$641,A5) -> 30 | D5: 28、31
A6: 8 | B6: 在餐馆用餐 | C6: =COUNTIF(生存汉语词汇表!$B$2:$B$641,A6) -> 13 | D6: 36
A7: 9 | B7: 方位和地址 | C7: =COUNTIF(生存汉语词汇表!$B$2:$B$641,A7) -> 28 | D7: 40、42
A8: 10 | B8: 问路 | C8: =COUNTIF(生存汉语词汇表!$B$2:$B$641,A8) -> 14 | D8: 46
A9: 11 | B9: 打车 | C9: =COUNTIF(生存汉语词汇表!$B$2:$B$641,A9) -> 17 | D9: 49、51
A10: 12 | B10: 坐公交车 | C10: =COUNTIF(生存汉语词汇表!$B$2:$B$641,A10) -> 14 | D10: 54
A11: 13 | B11: 坐地铁 | C11: =COUNTIF(生存汉语词汇表!$B$2:$B$641,A11) -> 18 | D11: 57、59、60
A12: 14 | B12: 坐火车 | C12: =COUNTIF(生存汉语词汇表!$B$2:$B$641,A12) -> 15 | D12: 63、65
A13: 15 | B13: 坐飞机 | C13: =COUNTIF(生存汉语词汇表!$B$2:$B$641,A13) -> 28 | D13: 69、71
... A37: 39 | B37: 属相（十二生肖） | C37: =COUNTIF(生存汉语词汇表!$B$2:$B$641,A37) -> 10 | D37: 195
A38: 合计（按每课出现顺序，含重复词） | C38: =SUM(C2:C37) -> 640 | D38: 第1–3课为拼音教学，无正式词汇表

Sheet 说明
A1: 项目 | B1: 内容
A2: 教材 | B2: 《生存汉语一本通》 / An All-in-One Guide to Survival Chinese
A3: 整理范围 | B3: 第1–3课为拼音（韵母、声母、声调）教学，没有正式“动作/Movements”词汇表；主表从第4课《看菜单》整理至第39课《属相（十二生肖）》.
A4: 排序规则 | B4: 严格按每一课词汇表/动作表中的出现顺序整理；同一个词如果在后续课程再次出现，仍保留，便于直接按课制作闪卡。
A5: 主表规模 | B5: 640条按课出现词条（含重复）；579个唯一词形。
A6: 英文解释 | B6: 以教材英文释义为基准；扫描/OCR造成的明显错字已做规范化，个别释义为便于初学者理解做了简化。
A7: 拼音 | B7: 统一使用带声调拼音；对“行李、头发、发型、调皮、空、出差、重要”等多音字/轻声词进行了人工校正。
A8: 例句原则 | B8: 每个词提供2个原创、高频、短句；尽量使用本书或非常基础的生存汉语词汇，不使用复杂句式，适合直接改造成闪卡。
A9: 最常见词语搭配 | B9: 每词提供3个常见搭配/固定组合；量词、方位词、交通、看病、购物、酒店等场景优先使用真实生活中的高频搭配。
A10: 星号/专名 | B10: 教材中带“*”的菜名、地名、专名等保留，并在“备注”列标记，方便教师按学生水平决定是否纳入必背。
A11: 使用建议 | B11: 做闪卡时可将“汉字+拼音+英文解释”作为正面/核心信息，将两个例句和三个搭配作为背面扩展。
